imf_importer/__init__.py
imf_importer/_compliance.py
imf_importer/_imf2data_model.py
imf_importer/_parsing.py
imf_importer/plugin.py
neat_imf_importer_plugin-0.1.1.dist-info/licenses/LICENSE
neat_imf_importer_plugin-0.1.1.dist-info/METADATA
neat_imf_importer_plugin-0.1.1.dist-info/WHEEL
neat_imf_importer_plugin-0.1.1.dist-info/entry_points.txt
neat_imf_importer_plugin-0.1.1.dist-info/top_level.txt
neat_imf_importer_plugin-0.1.1.dist-info/RECORD
