Metadata-Version: 2.4
Name: neat-imf-importer-plugin
Version: 0.1.1
Summary: IMF Importer Plugin for NEAT
Author-email: Bård Henning Tvedt <bard.tvedt@webstep.no>, Arne Måge <arne.mage@webstep.no>, Nikola Vasiljevic <nikola.vasiljevic@cognite.com>
License-Expression: Apache-2.0
Requires-Python: >=3.10
License-File: LICENSE
Requires-Dist: cognite-neat>=0.123.4
Dynamic: license-file
